[
  {
    "id": "marcelo-tasso",
    "displayName": "Marcelo Tasso",
    "aliases": ["Marcelo Tasso"]
  },
  {
    "id": "lucas-taveira-follis",
    "displayName": "Lucas Taveira Follis",
    "aliases": ["Lucas Taveira Follis", "Lucas Taveira Follis "]
  },
  {
    "id": "flavia-follis-bartolomeo",
    "displayName": "Flavia Follis Bartolomeo",
    "aliases": ["Flavia Follis Bartolomeo"]
  },
  {
    "id": "jacques-bartolomeo",
    "displayName": "Jacques Bartolomeo",
    "aliases": ["Jacques Bartolomeo"]
  },
  {
    "id": "rose",
    "displayName": "Rose Follis Tasso",
    "aliases": ["ROSE", "Rose", "Rose Follis Tasso"]
  },
  {
    "id": "lara-vieira-balieiro-tasso",
    "displayName": "Lara Vieira Balieiro Tasso",
    "aliases": ["Lara Vieira Balieiro Tasso"]
  },
  {
    "id": "helio-tasso-junior",
    "displayName": "Hélio Tasso Júnior",
    "aliases": ["Hélio Tasso Júnior", "Helio Tasso Junior"]
  },
  {
    "id": "vinicius-follis-tasso",
    "displayName": "Vinicius Follis Tasso",
    "aliases": ["Vinicius Follis Tasso", "Vinícius Follis Tasso"]
  },
  {
    "id": "mayara-gielow",
    "displayName": "Mayara Gielow",
    "aliases": ["Mayara Gielow"]
  },
  {
    "id": "jose-roberto-follis",
    "displayName": "José Roberto Follis",
    "aliases": ["José Roberto Follis", "Jose Roberto Follis"]
  }
]
